test/excel/__init__.py
test/excel/test_XLSX.py
test/pca/__init__.py
test/pca/test_matcher.py
test/time/__init__.py
test/time/test_counter.py
test/time/test_dateUtils.py
test/time/test_stopwatch.py
zeroinger/__init__.py
zeroinger/__version__.py
zeroinger/compression/__init__.py
zeroinger/compression/abs_cfu.py
zeroinger/compression/cfu_7z.py
zeroinger/config/__init__.py
zeroinger/config/config_parser_util.py
zeroinger/excel/__init__.py
zeroinger/excel/csv.py
zeroinger/excel/xlsx.py
zeroinger/file/__init__.py
zeroinger/file/path_util.py
zeroinger/msg/__init__.py
zeroinger/msg/ding.py
zeroinger/msg/feishu.py
zeroinger/pca/__init__.py
zeroinger/pca/adcode.tsv
zeroinger/pca/adcode_loader.py
zeroinger/pca/alias_builder.py
zeroinger/pca/area.py
zeroinger/pca/area2street_village.json
zeroinger/pca/matcher.py
zeroinger/pca/nations.txt
zeroinger/pca/script_gen_area2street_village.py
zeroinger/text/__init__.py
zeroinger/text/string.py
zeroinger/text/text_file.py
zeroinger/time/__init__.py
zeroinger/time/counter.py
zeroinger/time/dateutils.py
zeroinger/time/stopwatch.py
zeroinger-1.2.8.dist-info/LICENSE
zeroinger-1.2.8.dist-info/METADATA
zeroinger-1.2.8.dist-info/WHEEL
zeroinger-1.2.8.dist-info/top_level.txt
zeroinger-1.2.8.dist-info/RECORD
