Metadata-Version: 2.1
Name: zeroinger
Version: 1.2.8
Summary: group of tools for data process
Home-page: https://github.com/liangjz92/zeroinger-utils
Author: liangjz
Author-email: liangjianzeng@qq.com   
License: MIT
Platform: UNKNOWN
Classifier: License :: OSI Approved :: MIT License
Classifier: Programming Language :: Python
Classifier: Programming Language :: Python :: 3
Classifier: Programming Language :: Python :: 3.6
Classifier: Programming Language :: Python :: Implementation :: CPython
Classifier: Programming Language :: Python :: Implementation :: PyPy
Requires-Python: >=3.6.0
License-File: LICENSE
Requires-Dist: requests
Requires-Dist: logzero
Requires-Dist: arrow
Requires-Dist: configparser
Requires-Dist: pyexcel
Requires-Dist: pyahocorasick
Requires-Dist: dataclasses
Requires-Dist: python-dateutil
Requires-Dist: xlrd (<=1.2.0)
